_combinatorial.cpython-312-x86_64-linux-gnu.so
combin/__init__.py
combin/combinatorial.py
combin/include/combin/combin_ranges.h
combin/include/combin/combinatorial.h
combin/include/combin/utility/set_utilities.h
combin/include/combin/utility/short_alloc.h
combin/include/combin/utility/combinations.h
combin-0.1.7.dist-info/LICENSE
combin-0.1.7.dist-info/WHEEL
combin-0.1.7.dist-info/RECORD
combin-0.1.7.dist-info/METADATA
