Metadata-Version: 2.1
Name: combin
Version: 0.1.7
Author-Email: Matt Piekenbrock <matt.piekenbrock@gmail.com>
License:                                  Apache License
Classifier: Intended Audience :: Science/Research
Classifier: Development Status :: 3 - Alpha
Classifier: License :: OSI Approved :: Apache Software License
Classifier: Programming Language :: Python :: 3
Requires-Python: >=3.8
Requires-Dist: numpy
Requires-Dist: more_itertools
Requires-Dist: pytest; extra == "test"
Requires-Dist: pytest-cov; extra == "test"
Requires-Dist: pytest-benchmark; extra == "test"
Requires-Dist: coverage; extra == "test"
Provides-Extra: test
